traceroute_win/__init__.py
traceroute_win/traceroute_win.py
traceroute_imt-1.5.0.dist-info/LICENCE
traceroute_imt-1.5.0.dist-info/METADATA
traceroute_imt-1.5.0.dist-info/WHEEL
traceroute_imt-1.5.0.dist-info/entry_points.txt
traceroute_imt-1.5.0.dist-info/top_level.txt
traceroute_imt-1.5.0.dist-info/RECORD
